nuclear_add/__init__.py
nuclear_add/backends.py
nuclear_add/core.py
nuclear_add/demo.py
nuclear_add/tracing.py
nuclear_add/types.py
nuclear_add-1.0.0.dist-info/METADATA
nuclear_add-1.0.0.dist-info/WHEEL
nuclear_add-1.0.0.dist-info/entry_points.txt
nuclear_add-1.0.0.dist-info/RECORD
