Metadata-Version: 2.4
Name: nuclear-add
Version: 1.0.0
Summary: The most paranoid addition ever created
Project-URL: Homepage, https://github.com/example/nuclear-add
Project-URL: Bug Tracker, https://github.com/example/nuclear-add/issues
Project-URL: Documentation, https://nuclear-add.readthedocs.io
Author-email: Nuclear Add Contributors <nuclear-add@example.com>
License: MIT
Keywords: addition,autodiff,interval-arithmetic,kahan-summation,math,numerical-computing,overkill,precision
Classifier: Development Status :: 4 - Beta
Classifier: Intended Audience :: Developers
Classifier: Intended Audience :: Science/Research
Classifier: License :: OSI Approved :: MIT License
Classifier: Operating System :: OS Independent
Classifier: Programming Language :: Python :: 3
Classifier: Programming Language :: Python :: 3.10
Classifier: Programming Language :: Python :: 3.11
Classifier: Programming Language :: Python :: 3.12
Classifier: Topic :: Scientific/Engineering :: Mathematics
Classifier: Topic :: Software Development :: Libraries :: Python Modules
Classifier: Typing :: Typed
Requires-Python: >=3.10
Provides-Extra: all
Requires-Dist: numba>=0.58.0; extra == 'all'
Requires-Dist: numpy>=1.24.0; extra == 'all'
Requires-Dist: pint>=0.23; extra == 'all'
Requires-Dist: sympy>=1.12; extra == 'all'
Provides-Extra: dev
Requires-Dist: black>=23.0; extra == 'dev'
Requires-Dist: mypy>=1.0; extra == 'dev'
Requires-Dist: pytest-cov>=4.0; extra == 'dev'
Requires-Dist: pytest>=7.0; extra == 'dev'
Requires-Dist: ruff>=0.1.0; extra == 'dev'
Provides-Extra: gpu
Provides-Extra: jit
Requires-Dist: numba>=0.58.0; extra == 'jit'
Provides-Extra: numpy
Requires-Dist: numpy>=1.24.0; extra == 'numpy'
Provides-Extra: symbolic
Requires-Dist: sympy>=1.12; extra == 'symbolic'
Provides-Extra: units
Requires-Dist: pint>=0.23; extra == 'units'
